LICENSE.md
MANIFEST.in
README.rst
pyproject.toml
requirements.core.txt
requirements.txt
setup.py
core_explore_keyword_registry_app/__init__.py
core_explore_keyword_registry_app/apps.py
core_explore_keyword_registry_app/settings.py
core_explore_keyword_registry_app/urls.py
core_explore_keyword_registry_app.egg-info/PKG-INFO
core_explore_keyword_registry_app.egg-info/SOURCES.txt
core_explore_keyword_registry_app.egg-info/dependency_links.txt
core_explore_keyword_registry_app.egg-info/requires.txt
core_explore_keyword_registry_app.egg-info/top_level.txt
core_explore_keyword_registry_app/permissions/__init__.py
core_explore_keyword_registry_app/permissions/discover.py
core_explore_keyword_registry_app/static/core_explore_keyword_registry_app/user/css/fancytree/fancytree.custom.css
core_explore_keyword_registry_app/static/core_explore_keyword_registry_app/user/css/search/filters.css
core_explore_keyword_registry_app/static/core_explore_keyword_registry_app/user/css/search/search.css
core_explore_keyword_registry_app/static/core_explore_keyword_registry_app/user/js/search/fancytree.custom.js
core_explore_keyword_registry_app/static/core_explore_keyword_registry_app/user/js/search/fancytree.custom.raw.js
core_explore_keyword_registry_app/static/core_explore_keyword_registry_app/user/js/search/filters.js
core_explore_keyword_registry_app/static/core_explore_keyword_registry_app/user/js/search/resource_type_icons_table.js
core_explore_keyword_registry_app/static/core_explore_keyword_registry_app/user/js/search/resource_type_icons_table.raw.js
core_explore_keyword_registry_app/static/core_explore_keyword_registry_app/user/js/search/search.js
core_explore_keyword_registry_app/static/core_explore_keyword_registry_app/user/js/search/tagit.custom.js
core_explore_keyword_registry_app/static/core_explore_keyword_registry_app/user/libs/jquery-shorten/1.1.0/jquery.shorten.js
core_explore_keyword_registry_app/templates/core_explore_common_app/user/results/data_source_info.html
core_explore_keyword_registry_app/templates/core_explore_common_app/user/results/data_source_results.html
core_explore_keyword_registry_app/templates/core_explore_keyword_app/user/index.html
core_explore_keyword_registry_app/templates/core_explore_keyword_registry_app/user/refinements.html
